tempor/VERSION
tempor/__init__.py
tempor/__main__.py
tempor/ansible.py
tempor/cli.py
tempor/constants.py
tempor/exceptions.py
tempor/packer.py
tempor/ssh.py
tempor/terraform.py
tempor/utils.py
tempor/apis/__init__.py
tempor/apis/api.py
tempor/apis/aws.py
tempor/apis/azure.py
tempor/apis/digitalocean.py
tempor/apis/gcp.py
tempor/apis/helpers.py
tempor/apis/linode.py
tempor/apis/vultr.py
tempor/config/config.yml
tempor/config/schema.yml
tempor/providers/aws/data-sources.tf
tempor/providers/aws/main.tf
tempor/providers/aws/output.tf
tempor/providers/aws/routing.tf
tempor/providers/aws/security_groups.tf
tempor/providers/aws/variables.tf
tempor/providers/aws/versions.tf
tempor/providers/aws/vpc.tf
tempor/providers/aws/external/name-generator.py
tempor/providers/aws/external/passwd-generator.py
tempor/providers/azure/data-sources.tf
tempor/providers/azure/main.tf
tempor/providers/azure/output.tf
tempor/providers/azure/variables.tf
tempor/providers/azure/versions.tf
tempor/providers/azure/external/name-generator.py
tempor/providers/azure/external/passwd-generator.py
tempor/providers/digitalocean/data-sources.tf
tempor/providers/digitalocean/main.tf
tempor/providers/digitalocean/output.tf
tempor/providers/digitalocean/variables.tf
tempor/providers/digitalocean/versions.tf
tempor/providers/digitalocean/external/name-generator.py
tempor/providers/digitalocean/files/.gitkeep
tempor/providers/digitalocean/files/cloud-init.yml
tempor/providers/gcp/data-sources.tf
tempor/providers/gcp/main.tf
tempor/providers/gcp/output.tf
tempor/providers/gcp/variables.tf
tempor/providers/gcp/versions.tf
tempor/providers/gcp/external/name-generator.py
tempor/providers/gcp/external/passwd-generator.py
tempor/providers/linode/data-sources.tf
tempor/providers/linode/main.tf
tempor/providers/linode/output.tf
tempor/providers/linode/variables.tf
tempor/providers/linode/versions.tf
tempor/providers/linode/external/name-generator.py
tempor/providers/linode/external/passwd-generator.py
tempor-0.10.3.dist-info/entry_points.txt
tempor-0.10.3.dist-info/licenses/LICENSE
tempor-0.10.3.dist-info/WHEEL
tempor-0.10.3.dist-info/METADATA
tempor-0.10.3.dist-info/RECORD
