Metadata-Version: 2.4
Name: tempor
Version: 0.10.3
Summary: Quick and Easy Infrastructure.
Author-email: Wh1t3Fox <dev@exploit.design>
Requires-Python: >=3.11
Classifier: Development Status :: 4 - Beta
Classifier: Intended Audience :: Developers
Classifier: License :: OSI Approved :: Apache Software License
Classifier: Programming Language :: Python :: 3.11
Classifier: Programming Language :: Python :: 3.12
Classifier: Programming Language :: Python :: 3.13
Classifier: Operating System :: MacOS :: MacOS X
Classifier: Operating System :: POSIX :: Linux
Classifier: Environment :: Console
License-File: LICENSE
Requires-Dist: ansible==11.5.0
Requires-Dist: ansible_runner==2.4.1
Requires-Dist: appdirs==1.4.4
Requires-Dist: boto3==1.38.0
Requires-Dist: google-api-python-client==2.167.0
Requires-Dist: jsonschema==4.23.0
Requires-Dist: PyYAML==6.0.2
Requires-Dist: python-terraform==0.10.1
Requires-Dist: requests==2.32.3
Requires-Dist: rich==14.0.0
Requires-Dist: ssh-config==0.1.5
Project-URL: Documentation, https://github.com/Wh1t3Fox/tempor
Project-URL: Source, https://github.com/Wh1t3Fox/tempor
